Metadata-Version: 2.1
Name: norconnect
Version: 0.0.12
Summary: Cloud Simplify is a package for handling aws services with simple functions 
Author: R Sanjeev Rao
Author-email: sanjeevrao.159.v@gmail.com
Keywords: python,AWS,aws,simplify,simplifyaws
Classifier: Development Status :: 1 - Planning
Classifier: Intended Audience :: Developers
Classifier: Programming Language :: Python :: 3
Classifier: Operating System :: Unix
Classifier: Operating System :: MacOS :: MacOS X
Classifier: Operating System :: Microsoft :: Windows
License-File: LICENSE
